dpylint/__init__.py
dpylint/assets/__init__.py
dpylint/assets/events.py
dpylint/assets/shorthands.py
dpylint/checkers/__init__.py
dpylint/checkers/basechecker.py
dpylint/checkers/event_checker.py
dpylint/checkers/has_permissions_checker.py
dpylint/checkers/naming_convention_checker.py
dpylint-0.2.2.dist-info/LICENSE
dpylint-0.2.2.dist-info/METADATA
dpylint-0.2.2.dist-info/WHEEL
dpylint-0.2.2.dist-info/top_level.txt
dpylint-0.2.2.dist-info/RECORD
